[
{"form":"CoverLetter","special":"PageFromValue","prefix":"O.000","suffix":" ","field":"Courier,10","value":"
Fursht Lawste
1234 Demo Lane
Sumsity, TX 234543


Feb 31, 2031


Sum Kool Ko.
C/O Kool Cat
Austin, TX 564123-6436

RE: ATT:123-45-5678
  
To Kool Cat,

Totally love your product dude! Please send me more!

Sincerely,


Fursht Lawste
"},
{"form":"AARGform","prefix":"a.1","suffix":" ","field":"Nayme","value":"Gumpy Dufflodginus"},
{"form":"AARGform","prefix":"a.1","suffix":" ","field":"address","value":"523 Gumpalong^Mercy Lane, NY 5234652-234"},
{"form":"AARGform","prefix":"a.1","suffix":" ","field":"Note","value":"Walks in the Rain and drinks Marguita's Pina Colatas "},
{"form":"AARGform","prefix":"a.1","suffix":" ","field":"chkAttestation","value":"Yes"},
{"form":"AARGform","prefix":"a.1","suffix":" ","field":"Month","value":"13"},
{"form":"AARGform","prefix":"a.1","suffix":" ","field":"Year","value":"1583"},
{"form":"AARGform","prefix":"a.1","suffix":" ","field":"A1_01","value":"2"},
{"form":"AARGform","prefix":"a.1","suffix":" ","field":"A2_01","value":""},
{"form":"AARGform","prefix":"a.1","suffix":" ","field":"A3_01","value":"3"},
{"form":"AARGform","prefix":"a.1","suffix":" ","field":"A1_16","value":""},
{"form":"AARGform","prefix":"a.1","suffix":" ","field":"A2_16","value":""},
{"form":"AARGform","prefix":"a.1","suffix":" ","field":"A3_16","value":""},
{"form":"AARGform","prefix":"a.1","suffix":" ","field":"A1_02","value":""},
{"form":"AARGform","prefix":"a.1","suffix":" ","field":"A2_02","value":"4"},
{"form":"AARGform","prefix":"a.1","suffix":" ","field":"A3_02","value":""},
{"form":"AARGform","prefix":"a.1","suffix":" ","field":"A1_17","value":""},
{"form":"AARGform","prefix":"a.1","suffix":" ","field":"A2_17","value":""},
{"form":"AARGform","prefix":"a.1","suffix":" ","field":"A3_17","value":""},
{"form":"AARGform","prefix":"a.1","suffix":" ","field":"A1_03","value":"1"},
{"form":"AARGform","prefix":"a.1","suffix":" ","field":"A2_03","value":""},
{"form":"AARGform","prefix":"a.1","suffix":" ","field":"A3_03","value":""},
{"form":"AARGform","prefix":"a.1","suffix":" ","field":"A1_18","value":"1"},
{"form":"AARGform","prefix":"a.1","suffix":" ","field":"A2_18","value":""},
{"form":"AARGform","prefix":"a.1","suffix":" ","field":"A3_18","value":"22"},
{"form":"AARGform","prefix":"a.1","suffix":" ","field":"A1_04","value":""},
{"form":"AARGform","prefix":"a.1","suffix":" ","field":"A2_04","value":""},
{"form":"AARGform","prefix":"a.1","suffix":" ","field":"A3_04","value":""},
{"form":"AARGform","prefix":"a.1","suffix":" ","field":"A1_19","value":"6"},
{"form":"AARGform","prefix":"a.1","suffix":" ","field":"A2_19","value":""},
{"form":"AARGform","prefix":"a.1","suffix":" ","field":"A4_19","value":"-1"},
{"form":"AARGform","prefix":"a.1","suffix":" ","field":"A1_05","value":""},
{"form":"AARGform","prefix":"a.1","suffix":" ","field":"A2_05","value":""},
{"form":"AARGform","prefix":"a.1","suffix":" ","field":"A3_05","value":""},
{"form":"AARGform","prefix":"a.1","suffix":" ","field":"A1_20","value":"12"},
{"form":"AARGform","prefix":"a.1","suffix":" ","field":"A2_20","value":"13"},
{"form":"AARGform","prefix":"a.1","suffix":" ","field":"A3_20","value":"14"},
{"form":"AARGform","prefix":"a.1","suffix":" ","field":"A1_06","value":""},
{"form":"AARGform","prefix":"a.1","suffix":" ","field":"A2_06","value":""},
{"form":"AARGform","prefix":"a.1","suffix":" ","field":"A3_06","value":"3"},
{"form":"AARGform","prefix":"a.1","suffix":" ","field":"A1_21","value":""},
{"form":"AARGform","prefix":"a.1","suffix":" ","field":"A2_21","value":"6"},
{"form":"AARGform","prefix":"a.1","suffix":" ","field":"A3_21","value":"7"},
{"form":"AARGform","prefix":"a.1","suffix":" ","field":"A1_07","value":""},
{"form":"AARGform","prefix":"a.1","suffix":" ","field":"A2_07","value":""},
{"form":"AARGform","prefix":"a.1","suffix":" ","field":"A3_07","value":""},
{"form":"AARGform","prefix":"a.1","suffix":" ","field":"A1_22","value":"3"},
{"form":"AARGform","prefix":"a.1","suffix":" ","field":"A2_22","value":""},
{"form":"AARGform","prefix":"a.1","suffix":" ","field":"A3_22","value":"3"},
{"form":"AARGform","prefix":"a.1","suffix":" ","field":"A1_08","value":""},
{"form":"AARGform","prefix":"a.1","suffix":" ","field":"A2_08","value":""},
{"form":"AARGform","prefix":"a.1","suffix":" ","field":"A3_08","value":"3"},
{"form":"AARGform","prefix":"a.1","suffix":" ","field":"A1_23","value":""},
{"form":"AARGform","prefix":"a.1","suffix":" ","field":"A2_23","value":""},
{"form":"AARGform","prefix":"a.1","suffix":" ","field":"A3_23","value":""},
{"form":"AARGform","prefix":"a.1","suffix":" ","field":"A1_09","value":"6"},
{"form":"AARGform","prefix":"a.1","suffix":" ","field":"A2_09","value":""},
{"form":"AARGform","prefix":"a.1","suffix":" ","field":"A3_09","value":""},
{"form":"AARGform","prefix":"a.1","suffix":" ","field":"A1_24","value":""},
{"form":"AARGform","prefix":"a.1","suffix":" ","field":"A2_24","value":""},
{"form":"AARGform","prefix":"a.1","suffix":" ","field":"A3_24","value":"9"},
{"form":"AARGform","prefix":"a.1","suffix":" ","field":"A1_10","value":"2"},
{"form":"AARGform","prefix":"a.1","suffix":" ","field":"A2_10","value":""},
{"form":"AARGform","prefix":"a.1","suffix":" ","field":"A3_10","value":""},
{"form":"AARGform","prefix":"a.1","suffix":" ","field":"A1_25","value":""},
{"form":"AARGform","prefix":"a.1","suffix":" ","field":"A2_25","value":"8"},
{"form":"AARGform","prefix":"a.1","suffix":" ","field":"A3_25","value":"8"},
{"form":"AARGform","prefix":"a.1","suffix":" ","field":"A1_11","value":""},
{"form":"AARGform","prefix":"a.1","suffix":" ","field":"A2_11","value":""},
{"form":"AARGform","prefix":"a.1","suffix":" ","field":"A3_11","value":""},
{"form":"AARGform","prefix":"a.1","suffix":" ","field":"A1_26","value":""},
{"form":"AARGform","prefix":"a.1","suffix":" ","field":"A2_26","value":"1"},
{"form":"AARGform","prefix":"a.1","suffix":" ","field":"A3_26","value":""},
{"form":"AARGform","prefix":"a.1","suffix":" ","field":"A1_12","value":""},
{"form":"AARGform","prefix":"a.1","suffix":" ","field":"A2_12","value":""},
{"form":"AARGform","prefix":"a.1","suffix":" ","field":"A3_12","value":""},
{"form":"AARGform","prefix":"a.1","suffix":" ","field":"A1_27","value":""},
{"form":"AARGform","prefix":"a.1","suffix":" ","field":"A2_27","value":""},
{"form":"AARGform","prefix":"a.1","suffix":" ","field":"A3_27","value":""},
{"form":"AARGform","prefix":"a.1","suffix":" ","field":"A1_13","value":""},
{"form":"AARGform","prefix":"a.1","suffix":" ","field":"A2_13","value":""},
{"form":"AARGform","prefix":"a.1","suffix":" ","field":"A3_13","value":""},
{"form":"AARGform","prefix":"a.1","suffix":" ","field":"A1_28","value":""},
{"form":"AARGform","prefix":"a.1","suffix":" ","field":"A2_28","value":"3"},
{"form":"AARGform","prefix":"a.1","suffix":" ","field":"A3_28","value":""},
{"form":"AARGform","prefix":"a.1","suffix":" ","field":"A1_14","value":""},
{"form":"AARGform","prefix":"a.1","suffix":" ","field":"A2_14","value":""},
{"form":"AARGform","prefix":"a.1","suffix":" ","field":"A3_14","value":"4"},
{"form":"AARGform","prefix":"a.1","suffix":" ","field":"A1_29","value":""},
{"form":"AARGform","prefix":"a.1","suffix":" ","field":"A2_29","value":"1"},
{"form":"AARGform","prefix":"a.1","suffix":" ","field":"A3_29","value":""},
{"form":"AARGform","prefix":"a.1","suffix":" ","field":"A1_15","value":""},
{"form":"AARGform","prefix":"a.1","suffix":" ","field":"A2_15","value":"1"},
{"form":"AARGform","prefix":"a.1","suffix":" ","field":"A3_15","value":""},
{"form":"AARGform","prefix":"a.1","suffix":" ","field":"A1_30","value":"44"},
{"form":"AARGform","prefix":"a.1","suffix":" ","field":"A2_30","value":""},
{"form":"AARGform","prefix":"a.1","suffix":" ","field":"A3_30","value":"5"},
{"form":"AARGform","prefix":"a.1","suffix":" ","field":"A1_31","value":""},
{"form":"AARGform","prefix":"a.1","suffix":" ","field":"A2_31","value":""},
{"form":"AARGform","prefix":"a.1","suffix":" ","field":"A3_31","value":"2"},
{"form":"LengthyLatinDocument", "pages":"5","prefix":"a.2","suffix":" ","field":"doesntMatter","value":"laLa"},
{"form":"AARGform","prefix":"a.3","suffix":" ","field":"Nayme","value":"Glumpy McDumpyface"},
{"form":"AARGform","prefix":"a.3","suffix":" ","field":"address","value":"523 Floaty McFloat Face Road^Mercy Lane, NY 5234652-234"},
{"form":"AARGform","prefix":"a.3","suffix":" ","field":"Note","value":"Walks in the Rain and drinks Marguita's Pina Colatas "},
{"form":"AARGform","prefix":"a.3","suffix":" ","field":"chkAttestation","value":"Yes"},
{"form":"AARGform","prefix":"a.3","suffix":" ","field":"Month","value":"1"},
{"form":"AARGform","prefix":"a.3","suffix":" ","field":"Year","value":"2022"},
{"form":"SUMMARY","special":"PageFromValue","prefix":"z.1","suffix":" ","field":"Courier,10","value":"USED FOR CHECKING PRINT JOB
The data was copied from the excel workbook:3013-Jun-12 22:46:54
Any documents with an odd number of pages will have a blank
page inserted after in order to facilitate double sided printing.
"}
]